lig_equation_solver/__init__.py
lig_equation_solver-1.0.1.dist-info/METADATA
lig_equation_solver-1.0.1.dist-info/WHEEL
lig_equation_solver-1.0.1.dist-info/licenses/LICENSE
lig_equation_solver-1.0.1.dist-info/RECORD
